pimmslearn/README.md
pimmslearn/__init__.py
pimmslearn/data_handling.py
pimmslearn/filter.py
pimmslearn/imputation.py
pimmslearn/logging.py
pimmslearn/model.py
pimmslearn/nb.py
pimmslearn/normalization.py
pimmslearn/sampling.py
pimmslearn/transform.py
pimmslearn/utils.py
pimmslearn/analyzers/__init__.py
pimmslearn/analyzers/analyzers.py
pimmslearn/analyzers/compare_predictions.py
pimmslearn/analyzers/diff_analysis.py
pimmslearn/cmd_interface/__init__.py
pimmslearn/cmd_interface/setup_diff_analysis_website.py
pimmslearn/cmd_interface/setup_imp_cp_website.py
pimmslearn/databases/__init__.py
pimmslearn/databases/diseases.py
pimmslearn/io/__init__.py
pimmslearn/io/dataloaders.py
pimmslearn/io/datasets.py
pimmslearn/io/datasplits.py
pimmslearn/io/format.py
pimmslearn/io/load.py
pimmslearn/io/types.py
pimmslearn/models/__init__.py
pimmslearn/models/ae.py
pimmslearn/models/analysis.py
pimmslearn/models/collab.py
pimmslearn/models/collect_dumps.py
pimmslearn/models/vae.py
pimmslearn/pandas/__init__.py
pimmslearn/pandas/calc_errors.py
pimmslearn/pandas/missing_data.py
pimmslearn/plotting/__init__.py
pimmslearn/plotting/data.py
pimmslearn/plotting/defaults.py
pimmslearn/plotting/errors.py
pimmslearn/plotting/plotly.py
pimmslearn/sklearn/__init__.py
pimmslearn/sklearn/ae_transformer.py
pimmslearn/sklearn/cf_transformer.py
pimmslearn/stats/__init__.py
pimms_learn-0.5.0.dist-info/LICENSE.md
pimms_learn-0.5.0.dist-info/METADATA
pimms_learn-0.5.0.dist-info/WHEEL
pimms_learn-0.5.0.dist-info/entry_points.txt
pimms_learn-0.5.0.dist-info/top_level.txt
pimms_learn-0.5.0.dist-info/RECORD
