Metadata-Version: 2.1
Name: pimms-learn
Version: 0.5.0
Summary: Imputing (MS-based prote-) omics data using self supervised deep learning models.
Author-email: Henry Webel <henry.webel@sund.ku.dk>
Project-URL: Bug Tracker, https://github.com/RasmussenLab/pimms/issues
Project-URL: Homepage, https://github.com/RasmussenLab/pimms
Classifier: License :: OSI Approved :: GNU General Public License v3 (GPLv3)
Classifier: Intended Audience :: Healthcare Industry
Classifier: Intended Audience :: Science/Research
Classifier: Programming Language :: Python :: 3
Classifier: Topic :: Scientific/Engineering :: Bio-Informatics
Requires-Python: >=3.8
License-File: LICENSE.md
Requires-Dist: njab >=0.0.8
Requires-Dist: numpy
Requires-Dist: matplotlib
Requires-Dist: pandas
Requires-Dist: plotly
Requires-Dist: torch
Requires-Dist: scikit-learn >=1.0
Requires-Dist: scipy
Requires-Dist: seaborn <0.13
Requires-Dist: fastai
Requires-Dist: omegaconf
Requires-Dist: tqdm
Requires-Dist: mrmr-selection
Requires-Dist: pingouin
Provides-Extra: docs
Requires-Dist: sphinx ; extra == 'docs'
Requires-Dist: sphinx-book-theme ; extra == 'docs'
Requires-Dist: myst-nb ; extra == 'docs'
Requires-Dist: ipywidgets ; extra == 'docs'
Requires-Dist: sphinx-new-tab-link !=0.2.2 ; extra == 'docs'
